Metadata-Version: 2.4
Name: bigraph-schema
Version: 1.0.0
Summary: A serializable type schema for compositional systems biology
Author: Eran Agmon, Ryan Spangler
Requires-Python: >=3.7
License-File: LICENSE
License-File: AUTHORS.md
Requires-Dist: fire
Requires-Dist: numpy
Requires-Dist: orjson
Requires-Dist: parsimonious
Requires-Dist: pint
Requires-Dist: plum-dispatch
Requires-Dist: pytest
Requires-Dist: ipdb
Requires-Dist: requests>=2.31.0
Requires-Dist: setuptools
Requires-Dist: twine>=4.0.2
Dynamic: license-file
